{
  "data": [
    {
      "engineName": "google",
      "orderHint": 1000,
      "webExtension": {
        "id": "google@search.mozilla.org",
        "version": "1.0"
      },
      "searchUrlGetParams": {
        "client": "firefox-b-d",
        "q": "{searchTerms}"
      },
      "telemetryId": "google-b-d",
      "appliesTo": [{
        "included": { "everywhere": true },
        "default": "yes"
      }, {
        "included": {
          "regions": ["ru", "tr", "by", "kz"],
          "locales": {
            "matches": ["ru", "tr", "be", "kk"],
            "startsWith": ["en"]
          },
          "telemetryId": "google"
        },
        "default": "no"
      }, {
        "included": {
          "regions": ["cn"],
          "locales": {
            "matches": ["zh-CN"]
          }
        },
        "default": "no"
      }, {
        "included": { "regions": ["us"] },
        "searchUrlGetParams": {
          "client": "firefox-b-1-d",
          "q": "{searchTerms}"
        },
        "telemetryId": "google-b-1-d"
      }],
      "aliases": ["@google"]
    },
    {
      "engineName": "bing",
      "webExtension": {
        "id": "bing@search.mozilla.org",
        "version": "1.0"
      },
      "searchUrlGetParams": {
        "q": "{searchTerms}",
        "pc": "MOZI"
      },
      "extraParams": [{
        "name": "form",
        "condition": "purpose",
        "purpose": "searchbar",
        "value": "MOZSBR"
      }, {
        "name": "form",
        "condition": "purpose",
        "purpose": "keyword",
        "value": "MOZLBR"
      }, {
        "name": "form",
        "condition": "purpose",
        "purpose": "contextmenu",
        "value": "MOZCON"
      }, {
        "name": "form",
        "condition": "purpose",
        "purpose": "homepage",
        "value": "MOZSPG"
      }, {
        "name": "form",
        "condition": "purpose",
        "purpose": "newtab",
        "value": "MOZTSB"
      }],
      "appliesTo": [{
        "included": {
          "locales": {
            "matches": [
              "ach", "af", "an", "ar", "ast", "az", "ca", "ca-valencia",
              "cak", "da", "de", "dsb", "el", "eo", "es-CL", "es-ES",
              "es-MX", "eu", "fa", "ff", "fi", "fr", "fy-NL", "gn",
              "gu-IN", "hi-IN", "hr", "hsb", "ia", "is", "it",
              "ja-JP-mac", "ja", "ka", "kab", "km", "kn", "lij", "lo",
              "lt", "mai", "mk", "ml", "ms", "my", "nb-NO", "ne-NP", "nl",
              "nn-NO", "oc", "or", "pa-IN", "pt-BR", "rm", "ro", "son",
              "sq", "sr", "sv-SE", "th", "tl", "trs", "uk", "ur", "uz",
              "wo", "xh", "zh-CN"
            ],
            "startsWith": ["bn", "en"]
          }
        }
      }, {
        "included": { "regions": ["default"] }
      }],
      "aliases": ["@bing"]
    },
    {
      "engineName": "baidu",
      "webExtension": {
        "id": "baidu@search.mozilla.org",
        "version": "1.0"
      },
      "telemetryId": "baidu",
      "searchUrlGetParams": {
        "wd": "{searchTerms}",
        "tn": "monline_7_dg",
        "ie": "utf-8"
      },
      "suggestUrlGetParams": {
        "wd": "{searchTerms}",
        "tn": "monline_7_dg",
        "ie": "utf-8",
        "action": "opensearch"
      },
      "appliesTo": [{
        "included": { "locales": { "matches": ["zh-CN"] } }
      }, {
        "included": {
          "regions": ["cn"],
          "locales": { "matches": ["zh-CN"] }
        },
        "default": "yes"
      }],
      "aliases": ["@\u767E\u5EA6", "@baidu"]
    },
    {
      "engineName": "amazon",
      "orderHint": 500,
      "webExtension": {
        "id": "amazondotcom@search.mozilla.org",
        "version": "1.1"
      },
      "telemetryId": "amazondotcom",
      "suggestUrlGetParams": {
        "field-keywords": "{searchTerms}",
        "ie": "{inputEncoding}",
        "mode": "blended",
        "tag": "mozilla-20",
        "sourceid": "Mozilla-search"
      },
      "appliesTo": [{
        "included": { "regions": ["default"] }
      }, {
        "included": {
          "locales": {
            "matches": [
              "ach", "af", "ar", "az", "bg", "cak", "en-US", "eo",
              "es-AR", "fa", "gn", "hy-AM", "ia", "is", "ka", "km",
              "lt", "mk", "ms", "my", "ro", "si", "th", "tl",
              "trs", "uz"
            ]
          }
        }
      }, {
        "included": {
          "regions": ["au"],
          "locales": {
            "matches": [
              "ach", "af", "ar", "az", "bg", "cak", "en-US", "eo",
              "es-AR", "fa", "gn", "hy-AM", "ia", "is", "ka", "km",
              "lt", "mk", "ms", "my", "ro", "si", "th", "tl",
              "trs", "uz"
            ]
          }
        },
        "webExtension": {
          "id": "amazon@search.mozilla.org",
          "version": "1.1",
          "locales": ["au"]
        },
        "telemetryId": "amazon-au"
      }, {
        "included": {
          "regions": ["ca"],
          "locales": {
            "matches": [
              "ach", "af", "ar", "az", "bg", "cak", "en-US", "eo",
              "es-AR", "fa", "gn", "hy-AM", "ia", "is", "ka", "km",
              "lt", "mk", "ms", "my", "ro", "si", "th", "tl",
              "trs", "uz"
            ]
          }
        },
        "webExtension": {
          "id": "amazon@search.mozilla.org",
          "version": "1.1",
          "locales": ["ca"]
        },
        "telemetryId": "amazon-ca"
      }, {
        "included": {
          "regions": ["fr"],
          "locales": {
            "matches": [
              "ach", "af", "ar", "az", "bg", "cak", "en-US", "eo",
              "es-AR", "fa", "gn", "hy-AM", "ia", "is", "ka", "km",
              "lt", "mk", "ms", "my", "ro", "si", "th", "tl",
              "trs", "uz"
            ]
          }
        },
        "webExtension": {
          "id": "amazon@search.mozilla.org",
          "version": "1.1",
          "locales": ["france"]
        },
        "telemetryId": "amazon-france",
        "searchUrlGetParams": {
          "field-keywords": "{searchTerms}",
          "ie": "{inputEncoding}",
          "mode": "blended",
          "tag": "firefox-fr-21",
          "sourceid":"Mozilla-search"
        }
      }, {
        "included": {
          "regions": ["gb"],
          "locales": {
            "matches": [
              "ach", "af", "ar", "az", "bg", "cak", "en-US", "eo",
              "es-AR", "fa", "gn", "hy-AM", "ia", "is", "ka", "km",
              "lt", "mk", "ms", "my", "ro", "si", "th", "tl",
              "trs", "uz"
            ]
          }
        },
        "webExtension": {
          "id": "amazon@search.mozilla.org",
          "version": "1.1",
          "locales": ["en-GB"]
        },
        "telemetryId": "amazon-en-GB",
        "searchUrlGetParams": {
          "field-keywords": "{searchTerms}",
          "ie": "{inputEncoding}",
          "mode": "blended",
          "tag": "firefox-uk-21",
          "sourceid":"Mozilla-search"
        }
      }],
      "aliases": ["amazon"]
    },
    {
      "engineName": "Amazon",
      "orderHint": 500,
      "webExtension": {
        "id": "amazon@search.mozilla.org",
        "version": "1.1"
      },
      "searchUrlGetParams": {
        "field-keywords": "{searchTerms}",
        "ie": "{inputEncoding}",
        "mode": "blended"
      },
      "appliesTo": [{
        "included": {
          "locales": { "matches": [
            "as", "bn", "bn-IN", "kn", "gu-IN", "mai", "ml", "mr",
            "or", "pa-IN", "ta", "te", "ur"
          ]}
        },
        "webExtension": {
          "locales": ["in"]
        },
        "telemetryId": "amazon-in"
      }, {
        "included": {
          "locales": { "matches": ["br", "ff", "fr", "son", "wo"] }
        },
        "webExtension": {
          "locales": ["france"]
        },
        "telemetryId": "amazon-france",
        "searchUrlGetParams": {
          "field-keywords": "{searchTerms}",
          "ie": "{inputEncoding}",
          "mode": "blended",
          "tag": "firefox-fr-21",
          "sourceid":"Mozilla-search"
        }
      }, {
        "included": {
          "regions": ["ca"],
          "locales": { "matches": ["br", "ff", "fr", "son", "wo"] }
        },
        "webExtension": {
          "locales": ["ca"]
        },
        "telemetryId": "amazon-ca"
      }, {
        "included": { "locales": { "matches": ["en-CA"] } },
        "webExtension": {
          "locales": ["ca"]
        },
        "telemetryId": "amazon-ca"
      }, {
        "included": { "locales": { "matches": ["ja-JP-mac", "ja"] } },
        "webExtension": {
          "locales": ["jp"]
        },
        "telemetryId": "amazon-jp",
        "searchUrlGetParams": {
          "field-keywords": "{searchTerms}",
          "ie": "{inputEncoding}",
          "mode": "blended",
          "tag": "mozillajapan-fx-22",
          "sourceid":"Mozilla-search"
        }
      }, {
        "included": { "locales": { "matches": ["it", "lij"] } },
        "webExtension": {
          "locales": ["it"]
        },
        "telemetryId": "amazon-it",
        "searchUrlGetParams": {
          "field-keywords": "{searchTerms}",
          "ie": "{inputEncoding}",
          "mode": "blended",
          "tag": "firefoxit-21",
          "sourceid":"Mozilla-search"
        }
      }, {
        "included": { "locales": { "matches": ["de", "dsb", "hsb"] } },
        "webExtension": {
          "locales": ["de"]
        },
        "telemetryId": "amazon-de",
        "searchUrlGetParams": {
          "field-keywords": "{searchTerms}",
          "ie": "{inputEncoding}",
          "mode": "blended",
          "tag": "firefox-de-21",
          "sourceid":"Mozilla-search"
        }
      }, {
        "included": {
          "locales": {
            "matches": [
              "cy", "da", "el", "en-GB", "eu", "ga-IE", "gd", "gl", "hr",
              "nb-NO", "nn-NO", "pt-PT", "sq", "sr"
            ]
          }
        },
        "webExtension": {
          "locales": ["en-GB"]
        },
        "telemetryId": "amazon-en-GB",
        "searchUrlGetParams": {
          "field-keywords": "{searchTerms}",
          "ie": "{inputEncoding}",
          "mode": "blended",
          "tag": "firefox-uk-21",
          "sourceid":"Mozilla-search"
        }
      }, {
        "included": {
          "regions": ["au"],
          "locales": {
            "matches": [
              "cy", "da", "el", "en-GB", "eu", "ga-IE", "gd", "gl", "hr",
              "nb-NO", "nn-NO", "pt-PT", "sq", "sr"
            ]
          }
        },
        "webExtension": {
          "locales": ["au"]
        },
        "telemetryId": "amazon-au"
      }],
      "aliases": ["amazon"]
    },
    {
      "engineName": "amazoncn",
      "orderHint": 500,
      "webExtension": {
        "id": "amazondotcn@search.mozilla.org",
        "version": "1.0"
      },
      "telemetryId": "amazondotcn",
      "suggestUrlGetParams": {
        "keywords": "{searchTerms}",
        "ix": "sunray",
        "pageletid": "headsearch",
        "searchType": "",
        "Go.x": "0",
        "Go.y": "0",
        "bestSaleNum": "0"
      },
      "appliesTo": [{
        "included": { "locales": { "matches": ["zh-CN"] } }
      }],
      "aliases": ["amazon"]
    },
    {
      "engineName": "ebay",
      "orderHint": 500,
      "webExtension": {
        "id": "ebay@search.mozilla.org",
        "version": "1.0"
      },
      "searchUrlGetParams": {
        "ff3": "4",
        "toolid": "20004",
        "campid": "5338192028",
        "customid": "",
        "mpre": "https://www.ebay.com/sch/{searchTerms}"
      },
      "appliesTo": [{
        "included": { "regions": ["default"] }
      }, {
        "included": { "locales": { "matches": ["en-US"] } },
        "excluded": { "regions": ["ru", "tr", "by", "kz"] }
      }, {
        "included": {
          "locales": { "matches": ["en-US"] },
          "regions": ["au"]
        },
        "webExtension": {
          "locales": ["au"]
        },
        "telemetryId": "ebay-au",
        "searchUrlGetParams": {
          "ff3": "4",
          "toolid": "20004",
          "campid": "5338192028",
          "customid": "",
          "mpre": "https://www.ebay.com.au/sch/{searchTerms}"
        }
      }, {
        "included": {
          "locales": { "matches": ["en-US"] },
          "regions": ["ie"]
        },
        "webExtension": {
          "locales": ["ie"]
        },
        "telemetryId": "ebay-ie",
        "searchUrlGetParams": {
          "ff3": "4",
          "toolid": "20004",
          "campid": "5338192028",
          "customid": "",
          "mpre": "https://www.ebay.ie/sch/{searchTerms}"
        }
      }, {
        "included": {
          "locales": { "matches": ["en-US"] },
          "regions": ["be"]
        },
        "webExtension": {
          "locales": ["be"]
        },
        "telemetryId": "ebay-be",
        "searchUrlGetParams": {
          "ff3": "4",
          "toolid": "20004",
          "campid": "5338192028",
          "customid": "",
          "mpre": "https://www.befr.ebay.be/sch/{searchTerms}"
        }
      }, {
        "included": { "locales": {
          "matches": ["an", "ast", "ca", "ca-valencia", "es-ES", "eu", "gl"]
        }},
        "webExtension": {
          "locales": ["es"]
        },
        "telemetryId": "ebay-es",
        "searchUrlGetParams": {
          "ff3": "4",
          "toolid": "20004",
          "campid": "5338192028",
          "customid": "",
          "mpre": "https://www.ebay.es/sch/{searchTerms}"
        }
      }, {
        "included": { "locales": { "matches": ["br", "fr", "wo"] }},
        "webExtension": {
          "locales": ["fr"]
        },
        "telemetryId": "ebay-fr",
        "searchUrlGetParams": {
          "ff3": "4",
          "toolid": "20004",
          "campid": "5338192028",
          "customid": "",
          "mpre": "https://www.ebay.fr/sch/{searchTerms}"
        }
      }, {
        "included": {
          "locales": { "matches": ["br", "fr", "wo"] },
          "regions": ["be"]
        },
        "webExtension": {
          "locales": ["be"]
        },
        "telemetryId": "ebay-be",
        "searchUrlGetParams": {
          "ff3": "4",
          "toolid": "20004",
          "campid": "5338192028",
          "customid": "",
          "mpre": "https://www.befr.ebay.be/sch/{searchTerms}"
        }
      }, {
        "included": {
          "locales": { "matches": ["br", "fr", "wo"] },
          "regions": ["ca"]
        },
        "webExtension": {
          "locales": ["ca"]
        },
        "telemetryId": "ebay-ca",
        "searchUrlGetParams": {
          "ff3": "4",
          "toolid": "20004",
          "campid": "5338192028",
          "customid": "",
          "mpre": "https://www.ebay.ca/sch/{searchTerms}"
        }
      }, {
        "included": {
          "locales": { "matches": ["br", "fr", "wo"] },
          "regions": ["ch"]
        },
        "webExtension": {
          "locales": ["ch"]
        },
        "telemetryId": "ebay-ch",
        "searchUrlGetParams": {
          "ff3": "4",
          "toolid": "20004",
          "campid": "5338192028",
          "customid": "",
          "mpre": "https://www.ebay.ch/sch/{searchTerms}"
        }
      }, {
        "included": { "locales": { "matches": ["cy", "en-GB", "gd"] }},
        "webExtension": {
          "locales": ["uk"]
        },
        "telemetryId": "ebay-uk",
        "searchUrlGetParams": {
          "ff3": "4",
          "toolid": "20004",
          "campid": "5338192028",
          "customid": "",
          "mpre": "https://www.ebay.co.uk/sch/{searchTerms}"
        }
      }, {
        "included": {
          "locales": { "matches": ["cy", "en-GB", "gd"] },
          "regions": ["au"]
        },
        "webExtension": {
          "locales": ["au"]
        },
        "telemetryId": "ebay-au",
        "searchUrlGetParams": {
          "ff3": "4",
          "toolid": "20004",
          "campid": "5338192028",
          "customid": "",
          "mpre": "https://www.ebay.com.au/sch/{searchTerms}"
        }
      }, {
        "included": {
          "locales": { "matches": ["cy", "en-GB", "gd"] },
          "regions": ["ie"]
        },
        "webExtension": {
          "locales": ["ie"]
        },
        "telemetryId": "ebay-ie"
      }, {
        "included": { "locales": { "matches": ["de", "dsb", "hsb"] }},
        "webExtension": {
          "locales": ["de"]
        },
        "telemetryId": "ebay-de",
        "searchUrlGetParams": {
          "ff3": "4",
          "toolid": "20004",
          "campid": "5338192028",
          "customid": "",
          "mpre": "https://www.ebay.de/sch/{searchTerms}"
        }
      }, {
        "included": {
          "locales": { "matches": ["de", "dsb", "hsb"] },
          "regions": ["at"]
        },
        "webExtension": {
          "locales": ["at"]
        },
        "telemetryId": "ebay-at",
        "searchUrlGetParams": {
          "ff3": "4",
          "toolid": "20004",
          "campid": "5338192028",
          "customid": "",
          "mpre": "https://www.ebay.at/sch/{searchTerms}"
        }
      }, {
        "included": {
          "locales": { "matches": ["de", "dsb", "hsb"] },
          "regions": ["ch"]
        },
        "webExtension": {
          "locales": ["ch"]
        },
        "telemetryId": "ebay-ch"
      }, {
        "included": { "locales": { "matches": ["en-CA"] }},
        "webExtension": {
          "locales": ["ca"]
        },
        "telemetryId": "ebay-ca",
        "searchUrlGetParams": {
          "ff3": "4",
          "toolid": "20004",
          "campid": "5338192028",
          "customid": "",
          "mpre": "https://www.ebay.ca/sch/{searchTerms}"
        }
      }, {
        "included": { "locales": { "matches": ["fy-NL", "nl"] }},
        "webExtension": {
          "locales": ["nl"]
        },
        "telemetryId": "ebay-nl",
        "searchUrlGetParams": {
          "ff3": "4",
          "toolid": "20004",
          "campid": "5338192028",
          "customid": "",
          "mpre": "https://www.ebay.nl/sch/{searchTerms}"
        }
      }, {
        "included": {
          "locales": { "matches": ["fy-NL", "nl"] },
          "regions": ["be"]
        },
        "webExtension": {
          "locales": ["be"]
        },
        "telemetryId": "ebay-be",
        "searchUrlGetParams": {
          "ff3": "4",
          "toolid": "20004",
          "campid": "5338192028",
          "customid": "",
          "mpre": "https://www.befr.ebay.be/sch/{searchTerms}"
        }
      }, {
        "included": { "locales": { "matches": ["ga-IE"] }},
        "webExtension": {
          "locales": ["ie"]
        },
        "telemetryId": "ebay-ie",
        "searchUrlGetParams": {
          "ff3": "4",
          "toolid": "20004",
          "campid": "5338192028",
          "customid": "",
          "mpre": "https://www.ebay.ie/sch/{searchTerms}"
        }
      }, {
        "included": { "locales": { "matches": ["it", "lij"] }},
        "webExtension": {
          "locales": ["it"]
        },
        "telemetryId": "ebay-it",
        "searchUrlGetParams": {
          "ff3": "4",
          "toolid": "20004",
          "campid": "5338192028",
          "customid": "",
          "mpre": "https://www.ebay.it/sch/{searchTerms}"
        }
      }, {
        "included": { "locales": { "matches": ["rm"] }},
        "webExtension": {
          "locales": ["ch"]
        },
        "telemetryId": "ebay-ch",
        "searchUrlGetParams": {
          "ff3": "4",
          "toolid": "20004",
          "campid": "5338192028",
          "customid": "",
          "mpre": "https://www.ebay.ch/sch/{searchTerms}"
        }
      }],
      "aliases": ["@ebay"]
    },
    {
      "engineName": "ddg",
      "orderHint": 500,
      "webExtension": {
        "id": "ddg@search.mozilla.org",
        "version": "1.0"
      },
      "telemetryId": "ddg",
      "extraParams": [{
        "name": "t",
        "condition": "purpose",
        "purpose": "searchbar",
        "value": "ffsb"
      }, {
        "name": "t",
        "condition": "purpose",
        "purpose": "keyword",
        "value": "ffab"
      }, {
        "name": "t",
        "condition": "purpose",
        "purpose": "contextmenu",
        "value": "ffcm"
      }, {
        "name": "t",
        "condition": "purpose",
        "purpose": "homepage",
        "value": "ffhp"
      }, {
        "name": "t",
        "condition": "purpose",
        "purpose": "newtab",
        "value": "ffnt"
      }],
      "appliesTo": [{
        "included": { "everywhere": true }
      }],
      "aliases": ["@duckduckgo", "@ddg"]
    },
    {
      "engineName": "yandex",
      "webExtension": {
        "id": "yandex@search.mozilla.org",
        "version": "1.0"
      },
      "extraParams": [{
        "name": "clid",
        "condition": "purpose",
        "purpose": "searchbar",
        "value": "2186618"
      }, {
        "name": "clid",
        "condition": "purpose",
        "purpose": "keyword",
        "value": "2186621"
      }, {
        "name": "clid",
        "condition": "purpose",
        "purpose": "contextmenu",
        "value": "2186623"
      }, {
        "name": "clid",
        "condition": "purpose",
        "purpose": "homepage",
        "value": "2186617"
      }, {
        "name": "clid",
        "condition": "purpose",
        "purpose": "newtab",
        "value": "2186620"
      }],
      "appliesTo": [{
        "default": "yes",
        "included": {
          "regions": ["ru", "tr", "by", "kz"],
          "locales": {
            "matches": ["ru", "tr", "be", "kk"],
            "startsWith": ["en"]
          }
        },
        "webExtension": {
          "locales": ["en"]
        },
        "telemetryId": "yandex-en"
      }, {
        "included": { "locales": { "matches": ["az"] }},
        "webExtension": {
          "locales": ["az"]
        },
        "telemetryId": "yandex-az"
      }, {
        "included": { "locales": { "matches": ["be"] }},
        "webExtension": {
          "locales": ["by"]
        },
        "telemetryId": "yandex-by"
      }, {
        "included": { "locales": { "matches": ["kk"] }},
        "webExtension": {
          "locales": ["kk"]
        },
        "telemetryId": "yandex-kk"
      }, {
        "included": { "locales": { "matches": ["ru"] }},
        "webExtension": {
          "locales": ["ru"]
        },
        "telemetryId": "yandex-ru"
      }, {
        "included": { "locales": { "matches": ["tr"] }},
        "webExtension": {
          "locales": ["tr"]
        },
        "telemetryId": "yandex-tr"
      }],
      "aliases": ["@\u044F\u043D\u0434\u0435\u043A\u0441", "@yandex"]
    },
    {
      "engineName": "allaannonser-sv-SE",
      "webExtension": {
        "id": "allaannonser-sv-SE@search.mozilla.org",
        "version": "1.2"
      },
      "appliesTo": [{ "included": { "locales": { "matches": ["sv-SE"]}}}]
    },
    {
      "engineName": "allegro-pl",
      "webExtension": {
        "id": "allegro-pl@search.mozilla.org",
        "version": "1.0"
      },
      "appliesTo": [{ "included": { "locales": { "matches": ["pl"]}}}]
    },
    {
      "engineName": "atlas-sk",
      "webExtension": {
        "id": "atlas-sk@search.mozilla.org",
        "version": "1.0"
      },
      "appliesTo": [{ "included": { "locales": { "matches": ["sk"]}}}]
    },
    {
      "engineName": "azerdict",
      "webExtension": {
        "id": "azerdict@search.mozilla.org",
        "version": "1.0"
      },
      "appliesTo": [{ "included": { "locales": { "matches": ["az"]}}}]
    },
    {
      "engineName": "azet-sk",
      "webExtension": {
        "id": "azet-sk@search.mozilla.org",
        "version": "1.0"
      },
      "appliesTo": [{ "included": { "locales": { "matches": ["sk"]}}}]
    },
    {
      "engineName": "bbc-alba",
      "webExtension": {
        "id": "bbc-alba@search.mozilla.org",
        "version": "1.0"
      },
      "appliesTo": [{ "included": { "locales": { "matches": ["gd"]}}}]
    },
    {
      "engineName": "bok-NO",
      "webExtension": {
        "id": "bok-NO@search.mozilla.org",
        "version": "1.0"
      },
      "appliesTo": [{ "included": {
        "locales": { "matches": ["nb-NO", "nn-NO"]}
      }}]
    },
    {
      "engineName": "bolcom",
      "webExtension": {
        "id": "bolcom@search.mozilla.org",
        "version": "1.0"
      },
      "appliesTo": [{
        "included": { "locales": { "matches": ["fy-NL"]}},
        "webExtension": {
          "locales": ["fy-NL"]
        }
      }, {
        "included": { "locales": { "matches": ["nl"]}},
        "webExtension": {
          "locales": ["nl"]
        }
      }]
    },
    {
      "engineName": "ceneji",
      "webExtension": {
        "id": "ceneji@search.mozilla.org",
        "version": "1.0"
      },
      "appliesTo": [{ "included": { "locales": { "matches": ["sl"]}}}]
    },
    {
      "engineName": "chambers-en-GB",
      "webExtension": {
        "id": "chambers-en-GB@search.mozilla.org",
        "version": "1.0"
      },
      "appliesTo": [{ "included": { "locales": { "matches": ["en-GB"]}}}]
    },
    {
      "engineName": "coccoc",
      "webExtension": {
        "id": "coccoc@search.mozilla.org",
        "version": "1.0"
      },
      "appliesTo": [{ "included": { "locales": { "matches": ["vi"]}}}]
    },
    {
      "engineName": "daum-kr",
      "webExtension": {
        "id": "daum-kr@search.mozilla.org",
        "version": "1.0"
      },
      "appliesTo": [{ "included": { "locales": { "matches": ["ko"]}}}]
    },
    {
      "engineName": "diec2",
      "webExtension": {
        "id": "diec2@search.mozilla.org",
        "version": "1.2"
      },
      "appliesTo": [{
        "included": { "locales": { "matches": ["ca", "ca-valencia"]}}}]
    },
    {
      "engineName": "drae",
      "webExtension": {
        "id": "drae@search.mozilla.org",
        "version": "1.0"
      },
      "appliesTo": [{
        "included": { "locales": { "matches": ["es-AR", "es-CL", "es-ES"]}}
      }]
    },
    {
      "engineName": "ecosia",
      "webExtension": {
        "id": "ecosia@search.mozilla.org",
        "version": "1.0"
      },
      "appliesTo": [{ "included": { "locales": { "matches": ["de"]}}}]
    },
    {
      "engineName": "eki-ee",
      "webExtension": {
        "id": "eki-ee@search.mozilla.org",
        "version": "1.0"
      },
      "appliesTo": [{ "included": { "locales": { "matches": ["et"]}}}]
    },
    {
      "engineName": "eudict",
      "webExtension": {
        "id": "eudict@search.mozilla.org",
        "version": "1.0"
      },
      "appliesTo": [{ "included": { "locales": { "matches": ["hr"]}}}]
    },
    {
      "engineName": "faclair-beag",
      "webExtension": {
        "id": "faclair-beag@search.mozilla.org",
        "version": "1.0"
      },
      "appliesTo": [{ "included": { "locales": { "matches": ["gd"]}}}]
    },
    {
      "engineName": "flip",
      "webExtension": {
        "id": "flip@search.mozilla.org",
        "version": "1.0"
      },
      "appliesTo": [{ "included": { "locales": { "matches": ["kk"]}}}]
    },
    {
      "engineName": "freelang",
      "webExtension": {
        "id": "freelang@search.mozilla.org",
        "version": "1.0"
      },
      "appliesTo": [{ "included": { "locales": { "matches": ["br"]}}}]
    },
    {
      "engineName": "gulesider-NO",
      "webExtension": {
        "id": "gulesider-NO@search.mozilla.org",
        "version": "1.0"
      },
      "appliesTo": [{ "included": { "locales": { "matches": ["nn-NO", "nb-NO"]}}}]
    },
    {
      "engineName": "heureka-cz",
      "webExtension": {
        "id": "heureka-cz@search.mozilla.org",
        "version": "1.0"
      },
      "appliesTo": [{ "included": { "locales": { "matches": ["cs"]}}}]
    },
    {
      "engineName": "hotline-ua",
      "webExtension": {
        "id": "hotline-ua@search.mozilla.org",
        "version": "1.0"
      },
      "appliesTo": [{ "included": { "locales": { "matches": ["uk"]}}}]
    },
    {
      "engineName": "kannadastore",
      "webExtension": {
        "id": "kannadastore@search.mozilla.org",
        "version": "1.2"
      },
      "appliesTo": [{ "included": { "locales": { "matches": ["kn"]}}}]
    },
    {
      "engineName": "leo_ende_de",
      "webExtension": {
        "id": "leo_ende_de@search.mozilla.org",
        "version": "1.0"
      },
      "appliesTo": [{ "included": { "locales": { "matches": ["de", "dsb", "hsb" , "rm"]}}}]
    },
    {
      "engineName": "list-am",
      "webExtension": {
        "id": "list-am@search.mozilla.org",
        "version": "1.0"
      },
      "appliesTo": [{ "included": { "locales": { "matches": ["hy-AM"]}}}]
    },
    {
      "engineName": "longdo",
      "webExtension": {
        "id": "longdo@search.mozilla.org",
        "version": "1.0"
      },
      "appliesTo": [{ "included": { "locales": { "matches": ["th"]}}}]
    },
    {
      "engineName": "mailru",
      "webExtension": {
        "id": "mailru@search.mozilla.org",
        "version": "1.0"
      },
      "appliesTo": [{ "included": { "locales": { "matches": ["ru"]}}}]
    },
    {
      "engineName": "mapy-cz",
      "webExtension": {
        "id": "mapy-cz@search.mozilla.org",
        "version": "1.0"
      },
      "appliesTo": [{ "included": { "locales": { "matches": ["cs"]}}}]
    },
    {
      "engineName": "marktplaats",
      "webExtension": {
        "id": "marktplaats@search.mozilla.org",
        "version": "1.0"
      },
      "appliesTo": [{
        "included": { "locales": { "matches": ["fy-NL"]}},
        "webExtension": {
          "locales": ["fy-NL"]
        }
      }, {
        "included": { "locales": { "matches": ["nl"]}},
        "webExtension": {
          "locales": ["nl"]
        }
      }]
    },
    {
      "engineName": "mercadolibre",
      "webExtension": {
        "id": "mercadolibre@search.mozilla.org",
        "version": "1.0"
      },
      "appliesTo": [{
        "included": { "locales": { "matches": ["es-AR"]}},
        "webExtension": {
          "locales": ["ar"]
        }
      }, {
        "included": { "locales": { "matches": ["es-CL"]}},
        "webExtension": {
          "locales": ["cl"]
        }
      }, {
        "included": { "locales": { "matches": ["es-MX"]}},
        "webExtension": {
          "locales": ["mx"]
        }
      }]
    },
    {
      "engineName": "mercadolivre",
      "webExtension": {
        "id": "mercadolivre@search.mozilla.org",
        "version": "1.0"
      },
      "appliesTo": [{ "included": { "locales": { "matches": ["pt-BR"]}}}]
    },
    {
      "engineName": "morfix-dic",
      "webExtension": {
        "id": "morfix-dic@search.mozilla.org",
        "version": "1.1"
      },
      "appliesTo": [{ "included": { "locales": { "matches": ["he"]}}}]
    },
    {
      "engineName": "najdi-si",
      "webExtension": {
        "id": "najdi-si@search.mozilla.org",
        "version": "1.0"
      },
      "appliesTo": [{ "included": { "locales": { "matches": ["sl"]}}}]
    },
    {
      "engineName": "naver-kr",
      "webExtension": {
        "id": "naver-kr@search.mozilla.org",
        "version": "1.0"
      },
      "appliesTo": [{ "included": { "locales": { "matches": ["ko"]}}}]
    },
    {
      "engineName": "neti-ee",
      "webExtension": {
        "id": "neti-ee@search.mozilla.org",
        "version": "1.0"
      },
      "appliesTo": [{ "included": { "locales": { "matches": ["et"]}}}]
    },
    {
      "engineName": "odpiralni",
      "webExtension": {
        "id": "odpiralni@search.mozilla.org",
        "version": "1.0"
      },
      "appliesTo": [{ "included": { "locales": { "matches": ["sl"]}}}]
    },
    {
      "engineName": "olx",
      "webExtension": {
        "id": "olx@search.mozilla.org",
        "version": "1.0"
      },
      "appliesTo": [{ "included": { "locales": { "matches": ["bs"]}}}]
    },
    {
      "engineName": "oshiete-goo",
      "webExtension": {
        "id": "oshiete-goo@search.mozilla.org",
        "version": "1.0"
      },
      "appliesTo": [{ "included": { "locales": { "matches": ["ja-JP-mac", "jp"]}}}]
    },
    {
      "engineName": "osta-ee",
      "webExtension": {
        "id": "osta-ee@search.mozilla.org",
        "version": "1.0"
      },
      "appliesTo": [{ "included": { "locales": { "matches": ["et"]}}}]
    },
    {
      "engineName": "ozonru",
      "webExtension": {
        "id": "ozonru@search.mozilla.org",
        "version": "1.2"
      },
      "appliesTo": [{ "included": { "locales": { "matches": ["ru"]}}}]
    },
    {
      "engineName": "palasprint",
      "webExtension": {
        "id": "palasprint@search.mozilla.org",
        "version": "1.0"
      },
      "appliesTo": [{ "included": { "locales": { "matches": ["cy"]}}}]
    },
    {
      "engineName": "pazaruvaj",
      "webExtension": {
        "id": "pazaruvaj@search.mozilla.org",
        "version": "1.0"
      },
      "appliesTo": [{ "included": { "locales": { "matches": ["bg"]}}}]
    },
    {
      "engineName": "pogodak",
      "webExtension": {
        "id": "pogodak@search.mozilla.org",
        "version": "1.0"
      },
      "appliesTo": [{ "included": { "locales": { "matches": ["sr"]}}}]
    },
    {
      "engineName": "priberam",
      "webExtension": {
        "id": "priberam@search.mozilla.org",
        "version": "1.2"
      },
      "appliesTo": [{ "included": { "locales": { "matches": ["pt-PT"]}}}]
    },
    {
      "engineName": "priceru",
      "webExtension": {
        "id": "priceru@search.mozilla.org",
        "version": "1.0"
      },
      "appliesTo": [{ "included": { "locales": { "matches": ["ru"]}}}]
    },
    {
      "engineName": "prisjakt-sv-SE",
      "webExtension": {
        "id": "prisjakt-sv-SE@search.mozilla.org",
        "version": "1.0"
      },
      "appliesTo": [{ "included": { "locales": { "matches": ["sv-SE"]}}}]
    },
    {
      "engineName": "pwn-pl",
      "webExtension": {
        "id": "pwn-pl@search.mozilla.org",
        "version": "1.0"
      },
      "appliesTo": [{ "included": { "locales": { "matches": ["pl"]}}}]
    },
    {
      "engineName": "qwant",
      "webExtension": {
        "id": "qwant@search.mozilla.org",
        "version": "1.0"
      },
      "appliesTo": [{ "included": { "locales": { "matches": ["fr"]}}}]
    },
    {
      "engineName": "qxl-NO",
      "webExtension": {
        "id": "qxl-NO@search.mozilla.org",
        "version": "1.0"
      },
      "appliesTo": [{ "included": { "locales": { "matches": ["nb-NO", "nn-NO"]}}}]
    },
    {
      "engineName": "rakuten",
      "webExtension": {
        "id": "rakuten@search.mozilla.org",
        "version": "1.2"
      },
      "appliesTo": [{ "included": { "locales": { "matches": ["ja-JP-mac", "jp"]}}}]
    },
    {
      "engineName": "readmoo",
      "webExtension": {
        "id": "readmoo@search.mozilla.org",
        "version": "1.0"
      },
      "appliesTo": [{ "included": { "locales": { "matches": ["zh-TW"]}}}]
    },
    {
      "engineName": "salidzinilv",
      "webExtension": {
        "id": "salidzinilv@search.mozilla.org",
        "version": "1.0"
      },
      "appliesTo": [{ "included": { "locales": { "matches": ["ltg", "lv"]}}}]
    },
    {
      "engineName": "seznam-cz",
      "webExtension": {
        "id": "seznam-cz@search.mozilla.org",
        "version": "1.0"
      },
      "appliesTo": [{ "included": { "locales": { "matches": ["cs"]}}}]
    },
    {
      "engineName": "sslv",
      "webExtension": {
        "id": "sslv@search.mozilla.org",
        "version": "1.0"
      },
      "appliesTo": [{ "included": { "locales": { "matches": ["ltg", "lv"]}}}]
    },
    {
      "engineName": "tearma",
      "webExtension": {
        "id": "tearma@search.mozilla.org",
        "version": "1.0"
      },
      "appliesTo": [{ "included": { "locales": { "matches": ["ga-IE"]}}}]
    },
    {
      "engineName": "twitter",
      "webExtension": {
        "id": "twitter@search.mozilla.org",
        "version": "1.0"
      },
      "appliesTo": [{
        "included": { "locales": { "matches": [
          "default", "en-US", "ach", "an", "bs", "ca", "ca-valencia",
          "crh", "en-CA", "ga-IE", "gn", "hr", "ia", "ka", "kk", "km",
          "lo", "lt", "mai",  "ms", "my", "ne-NP", "oc", "pt-BR",
          "sl", "tl", "tr", "ur", "uz", "wo"
        ]}}
      }, {
        "included": { "locales": { "matches": ["ja-JP-mac", "ja"]}},
        "webExtension": {
          "locales": ["ja"]
        }
      }]
    },
    {
      "engineName": "tyda-sv-SE",
      "webExtension": {
        "id": "tyda-sv-SE@search.mozilla.org",
        "version": "1.0"
      },
      "appliesTo": [{ "included": { "locales": { "matches": ["sv-SE"]}}}]
    },
    {
      "engineName": "vatera",
      "webExtension": {
        "id": "vatera@search.mozilla.org",
        "version": "1.2"
      },
      "appliesTo": [{ "included": { "locales": { "matches": ["hu"]}}}]
    },
    {
      "engineName": "wiktionary",
      "webExtension": {
        "id": "wiktionary@search.mozilla.org",
        "version": "1.0"
      },
      "appliesTo": [{
        "included": { "locales": { "matches": ["te"]}},
        "webExtension": {
          "locales": ["te"]
        }
      }, {
        "included": { "locales": { "matches": ["oc"]}},
        "webExtension": {
          "locales": ["oc"]
        }
      }]
    },
    {
      "engineName": "wolnelektury-pl",
      "webExtension": {
        "id": "wolnelektury-pl@search.mozilla.org",
        "version": "1.0"
      },
      "appliesTo": [{ "included": { "locales": { "matches": ["pl"]}}}]
    },
    {
      "engineName": "yahoo-jp",
      "webExtension": {
        "id": "yahoo-jp@search.mozilla.org",
        "version": "1.0"
      },
      "appliesTo": [{ "included": { "locales": { "matches": ["ja-JP-mac", "ja"]}}}]
    },
    {
      "engineName": "yahoo-jp-auctions",
      "webExtension": {
        "id": "yahoo-jp-auctions@search.mozilla.org",
        "version": "1.2"
      },
      "appliesTo": [{ "included": { "locales": { "matches": ["ja-JP-mac", "ja"]}}}]
    },
    {
      "engineName": "zoznam-sk",
      "webExtension": {
        "id": "zoznam-sk@search.mozilla.org",
        "version": "1.2"
      },
      "appliesTo": [{ "included": { "locales": { "matches": ["sk"]}}}]
    },
    {
      "engineName": "wikipedia",
      "webExtension": {
        "id": "wikipedia@search.mozilla.org",
        "version": "1.0"
      },
      "appliesTo": [ {
        "included": { "everywhere": true }
      }, {
        "included": { "locales": { "matches": [
          "af", "an", "ar", "as", "ast", "az", "be", "bg",
          "br", "bs", "crh", "cy", "da", "de", "dsb",
          "el", "eo", "et", "eu", "fa", "fi", "fy-NL", "ga-IE",
          "gd", "gl", "gn", "he", "hr", "hsb", "hu", "ia",
          "id", "is", "it", "ka", "kab", "kk", "km", "kn",
          "lij", "lo", "lt", "ltg", "lv", "mk", "ml", "mr",
          "ms", "my", "nl", "oc", "or", "pl", "rm", "ro", "ru",
          "si", "sk", "sl", "sq", "sr", "sv-SE", "ta", "te",
          "th", "tl", "tr", "uk", "ur", "uz", "vi", "wo",
          "zh-CN", "zh-TW"
        ]}},
        "webExtension": {
          "locales": ["$USER_LOCALE"]
        }
      }, {
        "included": { "locales": { "matches": [ "be" ] } },
        "webExtension": {
          "locales": ["be", "be-tarask"]
        }
      }, {
        "included": { "locales": { "matches": [ "bn", "bn-BD", "bn-IN" ] } },
        "webExtension": {
          "locales": ["bn"]
        }
      }, {
        "included": { "locales": { "matches": [ "ca", "ca-valencia" ] } },
        "webExtension": {
          "locales": ["ca"]
        }
      }, {
        "included": { "locales": { "matches": [
          "cak", "es-AR", "es-CL", "es-ES", "es-MX", "trs"
        ]}},
        "webExtension": {
          "locales": ["es"]
        }
      }, {
        "included": { "locales": { "matches": [ "cs" ] } },
        "webExtension": {
          "locales": ["cz"]
        }
      }, {
        "included": { "locales": { "matches": [ "ff", "fr", "son" ] } },
        "webExtension": {
          "locales": ["fr"]
        }
      }, {
        "included": { "locales": { "matches": [ "gu-IN" ] } },
        "webExtension": {
          "locales": ["gu"]
        }
      }, {
        "included": { "locales": { "matches": [ "hi-IN" ] } },
        "webExtension": {
          "locales": ["hi"]
        }
      }, {
        "included": { "locales": { "matches": [ "hy-AM" ] } },
        "webExtension": {
          "locales": ["hy"]
        }
      }, {
        "included": { "locales": { "matches": [ "ja-JP-macos", "ja" ] } },
        "webExtension": {
          "locales": ["ja"]
        }
      }, {
        "included": { "locales": { "matches": [ "ko" ] } },
        "webExtension": {
          "locales": ["kr"]
        }
      }, {
        "included": { "locales": { "matches": [ "mai" ] } },
        "webExtension": {
          "locales": ["hi"]
        }
      }, {
        "included": { "locales": { "matches": [ "ml" ] } },
        "webExtension": {
          "locales": ["en", "ml"]
        }
      }, {
        "included": { "locales": { "matches": [ "nb-NO" ] } },
        "webExtension": {
          "locales": ["NO"]
        }
      }, {
        "included": { "locales": { "matches": [ "ne-NP" ] } },
        "webExtension": {
          "locales": ["ne"]
        }
      }, {
        "included": { "locales": { "matches": [ "nn-NO" ] } },
        "webExtension": {
          "locales": ["NN"]
        }
      }, {
        "included": { "locales": { "matches": [ "pa-IN" ] } },
        "webExtension": {
          "locales": ["pa"]
        }
      }, {
        "included": { "locales": { "matches": [ "pt-BR", "pt-PT" ] } },
        "webExtension": {
          "locales": ["pt"]
        }
      }]
    }
  ]
}
